court_queue/__init__.py
court_queue-1.0.4.dist-info/LICENSE
court_queue-1.0.4.dist-info/METADATA
court_queue-1.0.4.dist-info/WHEEL
court_queue-1.0.4.dist-info/top_level.txt
court_queue-1.0.4.dist-info/RECORD
