Metadata-Version: 2.1
Name: court-queue
Version: 1.0.4
Summary: Sophisticate Court Queue
Home-page: https://pypi.org/project/court-queue/
Author: khiat Mohammed Abderrezzak
Author-email: khiat.dev@gmail.com
License: MIT
Keywords: court queue
Classifier: Programming Language :: Python :: 3
Classifier: Operating System :: OS Independent
Classifier: License :: OSI Approved :: MIT License
Requires-Python: >=3.6
License-File: LICENSE
Requires-Dist: tabulate (>=0.9.0)
